{"type":"FeatureCollection","features":[{"type":"Feature","geometry":{"type":"Point","coordinates":[30.1595533,8.3531615]},"properties":{"date":"2026-06-25","name":"Y1 UNMISS Civil Affairs","description":"Civil Affairs survey indicates competition over remaining water points. "}},{"type":"Feature","geometry":{"type":"Point","coordinates":[30.1414397,8.2744326]},"properties":{"date":"2026-06-25","name":"Y1 UNMISS Civil Affairs","description":"Civil Affairs survey indicates competition over remaining water points. "}},{"type":"Feature","geometry":{"type":"Point","coordinates":[32.2298855,4.2196395]},"properties":{"date":"2026-06-30","name":"Y9 UNMISS Civil Affairs","description":"Reports that armed youth block rival groups from water point access."}},{"type":"Feature","geometry":{"type":"Point","coordinates":[32.2220285,4.2176661]},"properties":{"date":"2026-06-14","name":"Y9 UNMISS Civil Affairs","description":"Farmers report failed planting due to dry soils and late rains."}},{"type":"Feature","geometry":{"type":"Point","coordinates":[30.0727322,8.2738454]},"properties":{"date":"2026-06-25","name":"Y1 UNMISS Civil Affairs","description":"Civil Affairs survey indicates competition over remaining water points. "}}]}